testops_commons/__init__.py
testops_commons/report_lifecycle.py
testops_commons/report_storage.py
testops_commons/testops_connector.py
testops_commons/configuration/__init__.py
testops_commons/configuration/configuration.py
testops_commons/core/__init__.py
testops_commons/core/constants.py
testops_commons/generator/__init__.py
testops_commons/generator/generator.py
testops_commons/helper/__init__.py
testops_commons/helper/file_helper.py
testops_commons/helper/helper.py
testops_commons/model/__init__.py
testops_commons/model/models.py
testops_commons/uploader/__init__.py
testops_commons/uploader/uploader.py
testops_commons/uploader/utils.py
testops_commons-1.0.6.dist-info/LICENSE
testops_commons-1.0.6.dist-info/METADATA
testops_commons-1.0.6.dist-info/WHEEL
testops_commons-1.0.6.dist-info/top_level.txt
testops_commons-1.0.6.dist-info/RECORD
