Metadata-Version: 2.1
Name: testops-commons
Version: 1.0.6
Summary: TestOps Commons Python
Home-page: https://github.com/katalon-studio/testops-commons-python
Author: Katalon, LLC. (https://www.katalon.com)
Author-email: info@katalon.io
License: UNKNOWN
Keywords: Katalon,TestOps
Platform: UNKNOWN
Classifier: Operating System :: OS Independent
Requires-Python: >=3.6
License-File: LICENSE
Requires-Dist: requests
Requires-Dist: testops-api (>=1.0.2)
Requires-Dist: jsonpickle
